ml_processor/__init__.py
ml_processor/configuration.py
ml_processor/data_prep.py
ml_processor/eda_analysis.py
ml_processor/etl_processor.py
ml_processor/jsonSerializer.py
ml_processor/model_training.py
ml_processor/model_training_v0.py
ml_processor/outliers.py
ml_processor-0.5.20.dist-info/LICENSE.txt
ml_processor-0.5.20.dist-info/METADATA
ml_processor-0.5.20.dist-info/WHEEL
ml_processor-0.5.20.dist-info/top_level.txt
ml_processor-0.5.20.dist-info/RECORD
