Metadata-Version: 2.1
Name: ml-processor
Version: 0.5.20
Summary: Includes functions for performing econometrics tasks
Home-page: https://github.com/G-Geofrey/package_dev/tree/master/ml
Author: Geofrey Wanyama
Author-email: wanyamag17@gmail.com
License-File: LICENSE.txt
Requires-Dist: pandas
Requires-Dist: numpy (>=1.16)
Requires-Dist: matplotlib
Requires-Dist: seaborn
Requires-Dist: optbinning
Requires-Dist: snowflake-connector-python
Requires-Dist: snowflake.sqlalchemy
Requires-Dist: sqlalchemy
Requires-Dist: cryptography (>=3.4.8)
Requires-Dist: joblib
Requires-Dist: xgboost
Requires-Dist: statsmodels
Requires-Dist: hyperopt (>=0.2.7)
Requires-Dist: scipy
